reconify/__init__.py
reconify/reconifyAnthropicHandler.py
reconify/reconifyBedrockRuntimeHandler.py
reconify/reconifyCohereHandler.py
reconify/reconifyMistralHandler.py
reconify/reconifyOpenAIHandler.py
reconify/reconifyOpenAILegacyHandler.py
reconify/reconifyUniversalHandler.py
reconify-3.0.0.dist-info/METADATA
reconify-3.0.0.dist-info/WHEEL
reconify-3.0.0.dist-info/licenses/LICENSE
reconify-3.0.0.dist-info/RECORD
