Metadata-Version: 2.1
Name: reconify
Version: 3.0.0
Summary: A package for sending data to the Reconify platform
Project-URL: Homepage, https://github.com/reconify-com/reconify-pip#readme
Project-URL: Bug Tracker, https://github.com/reconify-com/reconify-pip/issues
Author-email: Reconify Team <services@reconify.com>
License-File: LICENSE
Classifier: License :: OSI Approved :: MIT License
Classifier: Operating System :: OS Independent
Classifier: Programming Language :: Python :: 3
Requires-Python: >=3.7
